robotframework_browser_translation/__init__.py
robotframework_browser_translation/translation_fi.json
robotframework_browser_translation-0.9.1.dist-info/LICENSE
robotframework_browser_translation-0.9.1.dist-info/METADATA
robotframework_browser_translation-0.9.1.dist-info/WHEEL
robotframework_browser_translation-0.9.1.dist-info/top_level.txt
robotframework_browser_translation-0.9.1.dist-info/RECORD
