Metadata-Version: 2.2
Name: robotframework-browser-translation
Version: 0.9.1
Summary: Robot Framework Browser library translation to Finnish languege
Author-email: Tatu Aalto <aalto.tatu@gmail.com>
License:                                  Apache License
Project-URL: Homepage, https://github.com/MarketSquare/robotframework-browser-translation-fi
Project-URL: Issues, https://github.com/MarketSquare/robotframework-browser-translation-fi/issues
Project-URL: Changelog, https://github.com/MarketSquare/robotframework-browser-translation-fi/blob/main/CHANGELOG.md
Keywords: Robot Framework,Browser
Classifier: Development Status :: 5 - Production/Stable
Classifier: Framework :: Robot Framework :: Library
Classifier: Topic :: Software Development :: Testing :: Acceptance
Classifier: Programming Language :: Python :: 3
Classifier: Programming Language :: Python :: 3.9
Classifier: Programming Language :: Python :: 3.10
Classifier: Programming Language :: Python :: 3.11
Classifier: Programming Language :: Python :: 3.12
Classifier: Programming Language :: Python :: 3.13
Classifier: License :: OSI Approved :: Apache Software License
Classifier: Operating System :: OS Independent
Requires-Python: >=3.9
License-File: LICENSE
Requires-Dist: robotframework-browser>=19.3.1
